{
  "type": "forge:conditional",
  "recipes": [
    {
      "conditions": [
        {
          "type": "simplecobalt:flag",
          "flag": "cobalt_recipes"
        }
      ],
      "recipe": {
        "type": "minecraft:crafting_shaped",
        "category": "equipment",
        "key": {
          "S": {
            "item": "simplecobalt:cobalt_ingot"
          },
          "T": {
            "tag": "forge:rods/wooden"
          }
        },
        "pattern": [
          " S ",
          " T ",
          " T "
        ],
        "result": {
          "item": "simplecobalt:cobalt_shovel"
        },
        "show_notification": true
      }
    }
  ]
}